permission_check/__init__.py
permission_check/permission_check.py
permission_check/tests/__init__.py
permission_check/tests/test_permission_check.py
permission_check/utils/__init__.py
permission_check-0.0.2.dist-info/LICENSE
permission_check-0.0.2.dist-info/METADATA
permission_check-0.0.2.dist-info/WHEEL
permission_check-0.0.2.dist-info/top_level.txt
permission_check-0.0.2.dist-info/RECORD
