Metadata-Version: 2.1
Name: permission-check
Version: 0.0.2
Summary: A simple, cross-platform, lightweight utility to check permission of files and folders in Python.
Home-page: https://github.com/srgrj/permission_check
Author: Somesh Garje
Author-email: someshgarje@gmail.com
License: UNKNOWN
Project-URL: Bug Tracker, https://github.com/srgrj/permission_check/issues
Platform: UNKNOWN
Classifier: Programming Language :: Python :: 3
Classifier: License :: OSI Approved :: MIT License
Classifier: Operating System :: OS Independent
Requires-Python: >=3.6
License-File: LICENSE
